LICENSE
MANIFEST.in
README.txt
requirements.txt
setup.py
lib/jnpr/__init__.py
lib/jnpr/junos/__init__.py
lib/jnpr/junos/console.py
lib/jnpr/junos/decorators.py
lib/jnpr/junos/device.py
lib/jnpr/junos/exception.py
lib/jnpr/junos/factcache.py
lib/jnpr/junos/jxml.py
lib/jnpr/junos/rpcmeta.py
lib/jnpr/junos/version.py
lib/jnpr/junos/cfg/__init__.py
lib/jnpr/junos/cfg/resource.py
lib/jnpr/junos/cfg/user.py
lib/jnpr/junos/cfg/user_ssh_key.py
lib/jnpr/junos/cfg/phyport/__init__.py
lib/jnpr/junos/cfg/phyport/base.py
lib/jnpr/junos/cfg/phyport/classic.py
lib/jnpr/junos/cfg/phyport/switch.py
lib/jnpr/junos/cfgro/__init__.py
lib/jnpr/junos/cfgro/srx.yml
lib/jnpr/junos/command/__init__.py
lib/jnpr/junos/command/chassis_fan.yml
lib/jnpr/junos/command/cm_error.yml
lib/jnpr/junos/command/ea_drd_error.yml
lib/jnpr/junos/command/ea_fi_error.yml
lib/jnpr/junos/command/ea_fi_statistics.yml
lib/jnpr/junos/command/ea_fo_statistics.yml
lib/jnpr/junos/command/ea_host_drop.yml
lib/jnpr/junos/command/ea_li_error.yml
lib/jnpr/junos/command/ea_lo_statistics.yml
lib/jnpr/junos/command/ea_pt_statistics.yml
lib/jnpr/junos/command/ea_wi_statistics.yml
lib/jnpr/junos/command/ea_wo_statistics.yml
lib/jnpr/junos/command/fpc_link_stats.yml
lib/jnpr/junos/command/fpc_memory.yml
lib/jnpr/junos/command/fpc_threads.yml
lib/jnpr/junos/command/host_loopback_status.yml
lib/jnpr/junos/command/ithrottle.yml
lib/jnpr/junos/command/jnh_exceptions.yml
lib/jnpr/junos/command/jnh_ifd_stream.yml
lib/jnpr/junos/command/jnhexceptionpkt.yml
lib/jnpr/junos/command/linecard_ethernet_statistics.yml
lib/jnpr/junos/command/ospf_neighbor.yml
lib/jnpr/junos/command/pci_error.yml
lib/jnpr/junos/command/pfe_ddos_policer.yml
lib/jnpr/junos/command/pre_classifier.yml
lib/jnpr/junos/command/scheduler_info.yml
lib/jnpr/junos/command/system_proc_ext.yml
lib/jnpr/junos/command/system_queues.yml
lib/jnpr/junos/command/task_io.yml
lib/jnpr/junos/command/toe_pfe.yml
lib/jnpr/junos/command/veriexec.yml
lib/junos_eznc_2.3.0.egg-info/PKG-INFO
lib/junos_eznc_2.3.0.egg-info/SOURCES.txt
lib/junos_eznc_2.3.0.egg-info/dependency_links.txt
lib/junos_eznc_2.3.0.egg-info/namespace_packages.txt
lib/junos_eznc_2.3.0.egg-info/requires.txt
lib/junos_eznc_2.3.0.egg-info/top_level.txt